[
  { "model_id": "model_iphone11", "brand_id": "brand_apple", "name": "iPhone 11" },
  { "model_id": "model_iphone11pro", "brand_id": "brand_apple", "name": "iPhone 11 Pro" },
  { "model_id": "model_iphone11promax", "brand_id": "brand_apple", "name": "iPhone 11 Pro Max" },
  { "model_id": "model_iphone12", "brand_id": "brand_apple", "name": "iPhone 12" },
  { "model_id": "model_iphone12mini", "brand_id": "brand_apple", "name": "iPhone 12 Mini" },
  { "model_id": "model_iphone12pro", "brand_id": "brand_apple", "name": "iPhone 12 Pro" },
  { "model_id": "model_iphone12promax", "brand_id": "brand_apple", "name": "iPhone 12 Pro Max" },
  { "model_id": "model_iphone13", "brand_id": "brand_apple", "name": "iPhone 13" },
  { "model_id": "model_iphone13mini", "brand_id": "brand_apple", "name": "iPhone 13 Mini" },
  { "model_id": "model_iphone13pro", "brand_id": "brand_apple", "name": "iPhone 13 Pro" },
  { "model_id": "model_iphone13promax", "brand_id": "brand_apple", "name": "iPhone 13 Pro Max" },
  { "model_id": "model_iphone14", "brand_id": "brand_apple", "name": "iPhone 14" },
  { "model_id": "model_iphone14plus", "brand_id": "brand_apple", "name": "iPhone 14 Plus" },
  { "model_id": "model_iphone14pro", "brand_id": "brand_apple", "name": "iPhone 14 Pro" },
  { "model_id": "model_iphone14promax", "brand_id": "brand_apple", "name": "iPhone 14 Pro Max" },
  { "model_id": "model_iphone15", "brand_id": "brand_apple", "name": "iPhone 15" },
  { "model_id": "model_iphone15plus", "brand_id": "brand_apple", "name": "iPhone 15 Plus" },
  { "model_id": "model_iphone15pro", "brand_id": "brand_apple", "name": "iPhone 15 Pro" },
  { "model_id": "model_iphone15promax", "brand_id": "brand_apple", "name": "iPhone 15 Pro Max" },
  { "model_id": "model_iphone16", "brand_id": "brand_apple", "name": "iPhone 16" },
  { "model_id": "model_iphone16plus", "brand_id": "brand_apple", "name": "iPhone 16 Plus" },
  { "model_id": "model_iphone16pro", "brand_id": "brand_apple", "name": "iPhone 16 Pro" },
  { "model_id": "model_iphone16promax", "brand_id": "brand_apple", "name": "iPhone 16 Pro Max" },
  { "model_id": "model_iphone17", "brand_id": "brand_apple", "name": "iPhone 17" },
  { "model_id": "model_iphone17plus", "brand_id": "brand_apple", "name": "iPhone 17 Plus" },
  { "model_id": "model_iphone17pro", "brand_id": "brand_apple", "name": "iPhone 17 Pro" },
  { "model_id": "model_iphone17promax", "brand_id": "brand_apple", "name": "iPhone 17 Pro Max" },
  { "model_id": "model_s21", "brand_id": "brand_samsung", "name": "Samsung Galaxy S21" },
  { "model_id": "model_s21ultra", "brand_id": "brand_samsung", "name": "Samsung Galaxy S21 Ultra" },
  { "model_id": "model_s22", "brand_id": "brand_samsung", "name": "Samsung Galaxy S22" },
  { "model_id": "model_s22ultra", "brand_id": "brand_samsung", "name": "Samsung Galaxy S22 Ultra" },
  { "model_id": "model_s23", "brand_id": "brand_samsung", "name": "Samsung Galaxy S23" },
  { "model_id": "model_s23ultra", "brand_id": "brand_samsung", "name": "Samsung Galaxy S23 Ultra" },
  { "model_id": "model_s24", "brand_id": "brand_samsung", "name": "Samsung Galaxy S24" },
  { "model_id": "model_s24ultra", "brand_id": "brand_samsung", "name": "Samsung Galaxy S24 Ultra" },
  { "model_id": "model_s25", "brand_id": "brand_samsung", "name": "Samsung Galaxy S25" },
  { "model_id": "model_s25ultra", "brand_id": "brand_samsung", "name": "Samsung Galaxy S25 Ultra" },
  { "model_id": "model_redmi10", "brand_id": "brand_xiaomi", "name": "Xiaomi Redmi 10" },
  { "model_id": "model_redmi11", "brand_id": "brand_xiaomi", "name": "Xiaomi Redmi 11" },
  { "model_id": "model_redmi12", "brand_id": "brand_xiaomi", "name": "Xiaomi Redmi 12" },
  { "model_id": "model_redmi13", "brand_id": "brand_xiaomi", "name": "Xiaomi Redmi 13" },
  { "model_id": "model_p40", "brand_id": "brand_huawei", "name": "Huawei P40" },
  { "model_id": "model_p50", "brand_id": "brand_huawei", "name": "Huawei P50" },
  { "model_id": "model_p60", "brand_id": "brand_huawei", "name": "Huawei P60" },
  { "model_id": "model_edge20", "brand_id": "brand_motorola", "name": "Motorola Edge 20" },
  { "model_id": "model_edge30", "brand_id": "brand_motorola", "name": "Motorola Edge 30" },
  { "model_id": "model_edge40", "brand_id": "brand_motorola", "name": "Motorola Edge 40" }
]
